{
  "timestamp": "2026-07-06T05:38:21.106Z",
  "sites": [
    {
      "id": "1337x",
      "status": "up",
      "latency": 38
    },
    {
      "id": "1ptba",
      "status": "up",
      "latency": 51
    },
    {
      "id": "52movie",
      "status": "up",
      "latency": 68
    },
    {
      "id": "acgrip",
      "status": "up",
      "latency": 367
    },
    {
      "id": "13city",
      "status": "up",
      "latency": 442
    },
    {
      "id": "0magnet",
      "status": "up",
      "latency": 577
    },
    {
      "id": "aidoruonline",
      "status": "up",
      "latency": 397
    },
    {
      "id": "52pt",
      "status": "up",
      "latency": 817
    },
    {
      "id": "alpharatio",
      "status": "up",
      "latency": 289
    },
    {
      "id": "aither",
      "status": "up",
      "latency": 715
    },
    {
      "id": "animebytes",
      "status": "up",
      "latency": 480
    },
    {
      "id": "alingpt",
      "status": "up",
      "latency": 887
    },
    {
      "id": "animez",
      "status": "up",
      "latency": 163
    },
    {
      "id": "animetosho",
      "status": "up",
      "latency": 363
    },
    {
      "id": "anirena",
      "status": "up",
      "latency": 227
    },
    {
      "id": "anisource",
      "status": "up",
      "latency": 503
    },
    {
      "id": "audiences",
      "status": "up",
      "latency": 147
    },
    {
      "id": "asiancinema",
      "status": "up",
      "latency": 516
    },
    {
      "id": "anthelion",
      "status": "up",
      "latency": 1030
    },
    {
      "id": "aura4k",
      "status": "up",
      "latency": 136
    },
    {
      "id": "avistaz",
      "status": "up",
      "latency": 329
    },
    {
      "id": "audiobookbay",
      "status": "up",
      "latency": 1037
    },
    {
      "id": "audionews",
      "status": "up",
      "latency": 1299
    },
    {
      "id": "azusa",
      "status": "up",
      "latency": 536
    },
    {
      "id": "baozi",
      "status": "up",
      "latency": 343
    },
    {
      "id": "beyondhd",
      "status": "up",
      "latency": 794
    },
    {
      "id": "bitporn",
      "status": "up",
      "latency": 799
    },
    {
      "id": "blutopia",
      "status": "up",
      "latency": 270
    },
    {
      "id": "broadcasthenet",
      "status": "up",
      "latency": 303
    },
    {
      "id": "brokenstones",
      "status": "up",
      "latency": 408
    },
    {
      "id": "bakabt",
      "status": "down",
      "latency": null
    },
    {
      "id": "btschool",
      "status": "up",
      "latency": 248
    },
    {
      "id": "bitpt",
      "status": "down",
      "latency": null
    },
    {
      "id": "capybarabr",
      "status": "up",
      "latency": 256
    },
    {
      "id": "byrbt",
      "status": "up",
      "latency": 1580
    },
    {
      "id": "carpt",
      "status": "up",
      "latency": 111
    },
    {
      "id": "cathoderaytube",
      "status": "up",
      "latency": 523
    },
    {
      "id": "btetree",
      "status": "up",
      "latency": 4914
    },
    {
      "id": "cbg",
      "status": "up",
      "latency": 1517
    },
    {
      "id": "chdbits",
      "status": "up",
      "latency": 347
    },
    {
      "id": "cdy",
      "status": "up",
      "latency": 3001
    },
    {
      "id": "cinematik",
      "status": "up",
      "latency": 458
    },
    {
      "id": "cinemaz",
      "status": "up",
      "latency": 106
    },
    {
      "id": "clearjav",
      "status": "up",
      "latency": 465
    },
    {
      "id": "crabpt",
      "status": "up",
      "latency": 342
    },
    {
      "id": "cspt",
      "status": "up",
      "latency": 366
    },
    {
      "id": "cgpeers",
      "status": "down",
      "latency": null
    },
    {
      "id": "darkpeers",
      "status": "up",
      "latency": 258
    },
    {
      "id": "cyanbug",
      "status": "up",
      "latency": 1064
    },
    {
      "id": "desigaane",
      "status": "up",
      "latency": 435
    },
    {
      "id": "digitalcore",
      "status": "up",
      "latency": 430
    },
    {
      "id": "dicmusic",
      "status": "up",
      "latency": 758
    },
    {
      "id": "discfan",
      "status": "up",
      "latency": 272
    },
    {
      "id": "dmhy",
      "status": "up",
      "latency": 134
    },
    {
      "id": "dstudio",
      "status": "up",
      "latency": 451
    },
    {
      "id": "dragonhd",
      "status": "up",
      "latency": 1823
    },
    {
      "id": "ehentai",
      "status": "up",
      "latency": 127
    },
    {
      "id": "dubhe",
      "status": "up",
      "latency": 1578
    },
    {
      "id": "exoticaz",
      "status": "up",
      "latency": 373
    },
    {
      "id": "exttorrents",
      "status": "up",
      "latency": 27
    },
    {
      "id": "empornium",
      "status": "up",
      "latency": 771
    },
    {
      "id": "filelist",
      "status": "up",
      "latency": 402
    },
    {
      "id": "freefarm",
      "status": "up",
      "latency": 633
    },
    {
      "id": "gazellegames",
      "status": "up",
      "latency": 876
    },
    {
      "id": "ggpt",
      "status": "up",
      "latency": 481
    },
    {
      "id": "greatposterwall",
      "status": "up",
      "latency": 820
    },
    {
      "id": "gtnet",
      "status": "up",
      "latency": 515
    },
    {
      "id": "gtorg",
      "status": "down",
      "latency": null
    },
    {
      "id": "gtru",
      "status": "up",
      "latency": 164
    },
    {
      "id": "haidan",
      "status": "up",
      "latency": 1268
    },
    {
      "id": "happyfappy",
      "status": "up",
      "latency": 169
    },
    {
      "id": "hdarea",
      "status": "up",
      "latency": 3726
    },
    {
      "id": "hdbao",
      "status": "up",
      "latency": 1756
    },
    {
      "id": "hdbits",
      "status": "up",
      "latency": 220
    },
    {
      "id": "hdcity",
      "status": "up",
      "latency": 772
    },
    {
      "id": "hdclone",
      "status": "up",
      "latency": 507
    },
    {
      "id": "hddolby",
      "status": "up",
      "latency": 46
    },
    {
      "id": "hdf",
      "status": "up",
      "latency": 318
    },
    {
      "id": "hdfans",
      "status": "up",
      "latency": 392
    },
    {
      "id": "hdhome",
      "status": "up",
      "latency": 412
    },
    {
      "id": "animelovers",
      "status": "down",
      "latency": null
    },
    {
      "id": "hdroute",
      "status": "up",
      "latency": 450
    },
    {
      "id": "hdsky",
      "status": "up",
      "latency": 1467
    },
    {
      "id": "hdspace",
      "status": "up",
      "latency": 586
    },
    {
      "id": "hdtime",
      "status": "up",
      "latency": 691
    },
    {
      "id": "hdtorrents",
      "status": "up",
      "latency": 521
    },
    {
      "id": "fearnopeer",
      "status": "down",
      "latency": null
    },
    {
      "id": "hdupt",
      "status": "up",
      "latency": 683
    },
    {
      "id": "hhanclub",
      "status": "up",
      "latency": 475
    },
    {
      "id": "hdvideo",
      "status": "up",
      "latency": 636
    },
    {
      "id": "hitpt",
      "status": "up",
      "latency": 260
    },
    {
      "id": "htpt",
      "status": "up",
      "latency": 513
    },
    {
      "id": "huno",
      "status": "up",
      "latency": 164
    },
    {
      "id": "hxpt",
      "status": "up",
      "latency": 81
    },
    {
      "id": "hdkylin",
      "status": "down",
      "latency": null
    },
    {
      "id": "iptorrents",
      "status": "up",
      "latency": 624
    },
    {
      "id": "itzmx",
      "status": "up",
      "latency": 2858
    },
    {
      "id": "ilolicon",
      "status": "down",
      "latency": null
    },
    {
      "id": "cinemageddon",
      "status": "down",
      "latency": null
    },
    {
      "id": "jptv4us",
      "status": "up",
      "latency": 272
    },
    {
      "id": "jpopsuki",
      "status": "up",
      "latency": 522
    },
    {
      "id": "keepfrds",
      "status": "up",
      "latency": 325
    },
    {
      "id": "karagarga",
      "status": "up",
      "latency": 581
    },
    {
      "id": "kelu",
      "status": "up",
      "latency": 699
    },
    {
      "id": "kufirc",
      "status": "up",
      "latency": 493
    },
    {
      "id": "kufei",
      "status": "up",
      "latency": 1314
    },
    {
      "id": "lajidui",
      "status": "up",
      "latency": 595
    },
    {
      "id": "agsvpt",
      "status": "down",
      "latency": null
    },
    {
      "id": "latteam",
      "status": "up",
      "latency": 313
    },
    {
      "id": "longpt",
      "status": "up",
      "latency": 85
    },
    {
      "id": "kunlun",
      "status": "up",
      "latency": 1390
    },
    {
      "id": "lst",
      "status": "up",
      "latency": 330
    },
    {
      "id": "lemonhdnet",
      "status": "up",
      "latency": 811
    },
    {
      "id": "luminarr",
      "status": "up",
      "latency": 248
    },
    {
      "id": "march",
      "status": "up",
      "latency": 538
    },
    {
      "id": "luckpt",
      "status": "up",
      "latency": 969
    },
    {
      "id": "midnightscene",
      "status": "up",
      "latency": 627
    },
    {
      "id": "momentpt",
      "status": "up",
      "latency": 154
    },
    {
      "id": "milkie",
      "status": "up",
      "latency": 382
    },
    {
      "id": "monikadesign",
      "status": "up",
      "latency": 469
    },
    {
      "id": "mteam",
      "status": "up",
      "latency": 336
    },
    {
      "id": "morethantv",
      "status": "up",
      "latency": 726
    },
    {
      "id": "musopia",
      "status": "up",
      "latency": 397
    },
    {
      "id": "muxuege",
      "status": "up",
      "latency": 440
    },
    {
      "id": "kamept",
      "status": "down",
      "latency": null
    },
    {
      "id": "myanonamouse",
      "status": "up",
      "latency": 625
    },
    {
      "id": "nebulance",
      "status": "up",
      "latency": 387
    },
    {
      "id": "mypt",
      "status": "up",
      "latency": 1253
    },
    {
      "id": "nekobt",
      "status": "up",
      "latency": 452
    },
    {
      "id": "ncore",
      "status": "up",
      "latency": 994
    },
    {
      "id": "nanyangpt",
      "status": "up",
      "latency": 1747
    },
    {
      "id": "nicept",
      "status": "up",
      "latency": 561
    },
    {
      "id": "nordicquality",
      "status": "up",
      "latency": 564
    },
    {
      "id": "nordicbytes",
      "status": "up",
      "latency": 682
    },
    {
      "id": "nexushd",
      "status": "up",
      "latency": 1372
    },
    {
      "id": "novahd",
      "status": "up",
      "latency": 440
    },
    {
      "id": "njtupt",
      "status": "up",
      "latency": 1774
    },
    {
      "id": "okpt",
      "status": "up",
      "latency": 654
    },
    {
      "id": "onlyencodes",
      "status": "up",
      "latency": 257
    },
    {
      "id": "oldtoonsworld",
      "status": "up",
      "latency": 611
    },
    {
      "id": "opencd",
      "status": "up",
      "latency": 401
    },
    {
      "id": "ourbits",
      "status": "up",
      "latency": 33
    },
    {
      "id": "orpheus",
      "status": "up",
      "latency": 505
    },
    {
      "id": "pandapt",
      "status": "up",
      "latency": 536
    },
    {
      "id": "piggo",
      "status": "up",
      "latency": 59
    },
    {
      "id": "oshenpt",
      "status": "up",
      "latency": 1060
    },
    {
      "id": "playletpt",
      "status": "up",
      "latency": 242
    },
    {
      "id": "pixelcove",
      "status": "up",
      "latency": 622
    },
    {
      "id": "pornolab",
      "status": "up",
      "latency": 373
    },
    {
      "id": "portugas",
      "status": "up",
      "latency": 454
    },
    {
      "id": "privatehd",
      "status": "up",
      "latency": 358
    },
    {
      "id": "pter",
      "status": "up",
      "latency": 709
    },
    {
      "id": "ptcafe",
      "status": "up",
      "latency": 1084
    },
    {
      "id": "ptgtk",
      "status": "up",
      "latency": 487
    },
    {
      "id": "pthome",
      "status": "up",
      "latency": 40
    },
    {
      "id": "nyaa",
      "status": "up",
      "latency": 4592
    },
    {
      "id": "ptfans",
      "status": "up",
      "latency": 1066
    },
    {
      "id": "ptlgs",
      "status": "up",
      "latency": 481
    },
    {
      "id": "ptneko",
      "status": "up",
      "latency": 665
    },
    {
      "id": "ptsbao",
      "status": "up",
      "latency": 689
    },
    {
      "id": "passthepopcorn",
      "status": "down",
      "latency": null
    },
    {
      "id": "ptzone",
      "status": "up",
      "latency": 95
    },
    {
      "id": "pussytorrents",
      "status": "up",
      "latency": 309
    },
    {
      "id": "ptskit",
      "status": "up",
      "latency": 1644
    },
    {
      "id": "pttime",
      "status": "up",
      "latency": 1855
    },
    {
      "id": "qingwa",
      "status": "up",
      "latency": 1372
    },
    {
      "id": "raingfh",
      "status": "up",
      "latency": 247
    },
    {
      "id": "redacted",
      "status": "up",
      "latency": 387
    },
    {
      "id": "railgunpt",
      "status": "up",
      "latency": 1411
    },
    {
      "id": "reelflix",
      "status": "up",
      "latency": 682
    },
    {
      "id": "retroflix",
      "status": "up",
      "latency": 572
    },
    {
      "id": "rousipro",
      "status": "up",
      "latency": 231
    },
    {
      "id": "sbpt",
      "status": "up",
      "latency": 81
    },
    {
      "id": "ptlao",
      "status": "down",
      "latency": null
    },
    {
      "id": "seedpool",
      "status": "up",
      "latency": 302
    },
    {
      "id": "secretcinema",
      "status": "up",
      "latency": 377
    },
    {
      "id": "shareisland",
      "status": "up",
      "latency": 447
    },
    {
      "id": "sewerpt",
      "status": "up",
      "latency": 481
    },
    {
      "id": "siqi",
      "status": "up",
      "latency": 405
    },
    {
      "id": "rutracker",
      "status": "up",
      "latency": 2085
    },
    {
      "id": "soulvoice",
      "status": "up",
      "latency": 424
    },
    {
      "id": "speedapp",
      "status": "up",
      "latency": 237
    },
    {
      "id": "skyeysnow",
      "status": "up",
      "latency": 1545
    },
    {
      "id": "sportscult",
      "status": "up",
      "latency": 312
    },
    {
      "id": "springsunday",
      "status": "up",
      "latency": 456
    },
    {
      "id": "starspace",
      "status": "up",
      "latency": 483
    },
    {
      "id": "sunnypt",
      "status": "up",
      "latency": 932
    },
    {
      "id": "superbits",
      "status": "up",
      "latency": 419
    },
    {
      "id": "tangpt",
      "status": "up",
      "latency": 412
    },
    {
      "id": "tccf",
      "status": "up",
      "latency": 1508
    },
    {
      "id": "tey",
      "status": "up",
      "latency": 1014
    },
    {
      "id": "thegeeks",
      "status": "up",
      "latency": 988
    },
    {
      "id": "thevault",
      "status": "up",
      "latency": 964
    },
    {
      "id": "tjupt",
      "status": "up",
      "latency": 446
    },
    {
      "id": "tlfbits",
      "status": "up",
      "latency": 157
    },
    {
      "id": "hudbt",
      "status": "down",
      "latency": null
    },
    {
      "id": "tokyotosho",
      "status": "up",
      "latency": 1891
    },
    {
      "id": "torrentleech",
      "status": "up",
      "latency": 180
    },
    {
      "id": "torrentscsv",
      "status": "up",
      "latency": 297
    },
    {
      "id": "totheglory",
      "status": "up",
      "latency": 248
    },
    {
      "id": "sjtu",
      "status": "down",
      "latency": null
    },
    {
      "id": "u2",
      "status": "up",
      "latency": 433
    },
    {
      "id": "ubits",
      "status": "up",
      "latency": 34
    },
    {
      "id": "ultrahd",
      "status": "up",
      "latency": 92
    },
    {
      "id": "uploadcx",
      "status": "up",
      "latency": 81
    },
    {
      "id": "vclib",
      "status": "up",
      "latency": 1160
    },
    {
      "id": "wintersakura",
      "status": "up",
      "latency": 216
    },
    {
      "id": "xingtan",
      "status": "up",
      "latency": 1357
    },
    {
      "id": "tu88",
      "status": "down",
      "latency": null
    },
    {
      "id": "xingyunge",
      "status": "up",
      "latency": 133
    },
    {
      "id": "yemapt",
      "status": "up",
      "latency": 162
    },
    {
      "id": "xingwan",
      "status": "up",
      "latency": 1606
    },
    {
      "id": "yinguskg",
      "status": "up",
      "latency": 1244
    },
    {
      "id": "yuscene",
      "status": "up",
      "latency": 831
    },
    {
      "id": "zhuque",
      "status": "up",
      "latency": 482
    },
    {
      "id": "zmpt",
      "status": "up",
      "latency": 359
    },
    {
      "id": "zrpt",
      "status": "up",
      "latency": 494
    },
    {
      "id": "rs",
      "status": "down",
      "latency": null
    },
    {
      "id": "sugoimusic",
      "status": "down",
      "latency": null
    },
    {
      "id": "tmpt",
      "status": "down",
      "latency": null
    },
    {
      "id": "zhixing",
      "status": "down",
      "latency": null
    }
  ]
}